NEBULA/__init__.py
NEBULA/core/__init__.py
NEBULA/core/baseInjector.py
NEBULA/core/errorTypes.py
NEBULA/core/history.py
NEBULA/core/injectionImpl.py
NEBULA/core/injector.py
NEBULA/core/legacy.py
NEBULA/core/legacyInjector.py
NEBULA/core/noiseLayer.py
NEBULA/core/trainingInjector.py
NEBULA/utils/__init__.py
NEBULA/utils/commons.py
NEBULA/utils/helper.py
NEBULA/utils/logging.py
NEBULANN-0.3.dist-info/LICENSE
NEBULANN-0.3.dist-info/METADATA
NEBULANN-0.3.dist-info/WHEEL
NEBULANN-0.3.dist-info/top_level.txt
NEBULANN-0.3.dist-info/RECORD
