Metadata-Version: 2.1
Name: NEBULANN
Version: 0.3
Summary: Error injection and quantized training lib for NNs
Author: Alexander Tepe
Author-email: alexander.tepe@hotmail.de
License: MIT
License-File: LICENSE
Requires-Dist: setuptools
Requires-Dist: tensorflow
Requires-Dist: numpy
Requires-Dist: python-dotenv
